shapely_extra/__init__.py
shapely_extra/angles.py
shapely_extra/area.py
shapely_extra/grid.py
shapely_extra/measure.py
shapely_extra/random.py
shapely_extra/shapes.py
shapely_extra/utils.py
shapely_extra-0.1.0.dist-info/METADATA
shapely_extra-0.1.0.dist-info/WHEEL
shapely_extra-0.1.0.dist-info/licenses/LICENSE
shapely_extra-0.1.0.dist-info/RECORD
